TablesRishit/__init__.py
TablesRishit/table.py
TablesRishit-0.1.1.dist-info/LICENSE
TablesRishit-0.1.1.dist-info/METADATA
TablesRishit-0.1.1.dist-info/WHEEL
TablesRishit-0.1.1.dist-info/top_level.txt
TablesRishit-0.1.1.dist-info/RECORD
